tree2gd_main.py
tree2gd/__init__.py
tree2gd/blastp.py
tree2gd/dollop.py
tree2gd/kaks.py
tree2gd/mcl.py
tree2gd/plot.py
tree2gd/seq.py
tree2gd/synteny.py
tree2gd/wgd.py
tree2gd/example_data/Alyrata.cds
tree2gd/example_data/Alyrata.pep
tree2gd/example_data/Athaliana.cds
tree2gd/example_data/Athaliana.pep
tree2gd/example_data/Brapa.cds
tree2gd/example_data/Brapa.pep
tree2gd/example_data/Cpapaya.cds
tree2gd/example_data/Cpapaya.pep
tree2gd/example_data/Crubella.cds
tree2gd/example_data/Crubella.pep
tree2gd/example_data/Esalsugineum.cds
tree2gd/example_data/Esalsugineum.pep
tree2gd/example_data/Tparvula.cds
tree2gd/example_data/Tparvula.pep
tree2gd/example_data/config.ini
tree2gd/example_data/example.tree
tree2gd/example_data/full_config.ini
tree2gd/software/Epal2nal.pl
tree2gd/software/KaKs_Calculator
tree2gd/software/PhyloMCL
tree2gd/software/SVM.R
tree2gd/software/Tree2GD
tree2gd/software/Tree2GD_draw.R
tree2gd/software/calculate_4DTV_correction.pl
tree2gd/software/diamond
tree2gd/software/dolloparsimony
tree2gd/software/iqtree
tree2gd/software/muscle
tree2gd/software/seqkit
tree2gd/software/trimal
Tree2gd-1.0.43.dist-info/LICENSE
Tree2gd-1.0.43.dist-info/METADATA
Tree2gd-1.0.43.dist-info/WHEEL
Tree2gd-1.0.43.dist-info/entry_points.txt
Tree2gd-1.0.43.dist-info/top_level.txt
Tree2gd-1.0.43.dist-info/RECORD
