Metadata-Version: 2.1
Name: Tree2gd
Version: 1.0.43
Summary: Tree2gd
Home-page: https://github.com/Dee-chen/Tree2gd
Author: Duoyuan chen
Author-email: 18110700097@fudan.edu.cn
License: GPL
Platform: UNKNOWN
Classifier: Programming Language :: Python :: 3.6
Classifier: License :: OSI Approved :: GNU General Public License v3 or later (GPLv3+)
Classifier: Operating System :: POSIX :: Linux
Requires-Python: >=3.6
License-File: LICENSE
Requires-Dist: configparser
Requires-Dist: matplotlib
Requires-Dist: argparse
Requires-Dist: coloredlogs
Requires-Dist: pyecharts
Requires-Dist: bio
Requires-Dist: jcvi
